anty/__init__.py
anty-0.1.2.dist-info/METADATA
anty-0.1.2.dist-info/WHEEL
anty-0.1.2.dist-info/top_level.txt
anty-0.1.2.dist-info/RECORD
