Metadata-Version: 2.4
Name: anty
Version: 0.1.2
Summary: No Description
Author-email: XichengWu <3390818557@qq.com>
License: MIT
Keywords: anty
Classifier: Programming Language :: Python :: 3
Classifier: License :: OSI Approved :: MIT License
Classifier: Operating System :: OS Independent
Requires-Python: >=3.10
Requires-Dist: setuptools>=75.3.2
